snpfc/__init__.py
snpfc/doCompare.py
snpfc/doFilter.py
snpfc/snpCompare.py
snpfc/snpFilter.py
snpfc/snpfc.py
snpfc-1.0.0.dist-info/METADATA
snpfc-1.0.0.dist-info/WHEEL
snpfc-1.0.0.dist-info/top_level.txt
snpfc-1.0.0.dist-info/RECORD
